<?xml version="1.0" encoding="UTF-8"?>
<DCOPData Version="1.0" Time="fre. okt 16 13:41:51 2020" Simulator="hpeesofsim">
 <Controller name="SP1">
  <SweepCondition>
   <P>freq: 5.0000000000000000e+08</P>
  </SweepCondition>
  <DC_OPDeclaration/>
  <DC_Voltages>
   <V>0: 0.0000000000000000e+00</V>
   <V>N__0: -2.5000000000000000e+00</V>
   <V>N__1: 0.0000000000000000e+00</V>
   <V>N__3: 0.0000000000000000e+00</V>
   <V>N__4: 2.8000000000000000e+01</V>
   <V>X1.Kap1.N__1: -2.4999766253978764e+00</V>
   <V>X1.Kap1.P1: -2.4999766253978764e+00</V>
   <V>X1.Kap1.P2: -2.4999532689787594e+00</V>
   <V>X1.Kap2.N__1: 0.0000000000000000e+00</V>
   <V>X1.Kap2.P1: 0.0000000000000000e+00</V>
   <V>X1.Kap2.P2: -2.4999766257482241e+00</V>
   <V>X1.Kap3.N__1: 2.7997777448037219e+01</V>
   <V>X1.Kap3.P1: 2.7997777448037219e+01</V>
   <V>X1.Kap3.P2: 0.0000000000000000e+00</V>
   <V>X1.N__1: 2.7997777448037219e+01</V>
   <V>X1.N__10: -2.4999766253978764e+00</V>
   <V>X1.N__12: 2.7997777448037198e+01</V>
   <V>X1.N__13: 2.7997495647382102e+01</V>
   <V>X1.N__14: 2.7997733829229425e+01</V>
   <V>X1.N__15: -2.4999532689787594e+00</V>
   <V>X1.N__17: -2.4999532670656825e+00</V>
   <V>X1.N__18: -2.4999766260985696e+00</V>
   <V>X1.N__19: -2.4999766257482237e+00</V>
   <V>X1.N__20: 0.0000000000000000e+00</V>
   <V>X1.N__21: 0.0000000000000000e+00</V>
   <V>X1.N__22: 2.7997821066844953e+01</V>
   <V>X1.N__23: -2.4999766257482241e+00</V>
   <V>X1.N__5: -2.4999999824958592e+00</V>
   <V>X1.N__6: 0.0000000000000000e+00</V>
   <V>X1.N__8: 0.0000000000000000e+00</V>
   <V>X1.X1.N__11: 2.7997495647382102e+01</V>
   <V>X1.X1.N__17: 2.7981065896456666e+01</V>
   <V>X1.X1.N__18: -2.4999522674113339e+00</V>
   <V>X1.X1.N__9: -2.4999532670656825e+00</V>
   <V>X1.X1.P1: -2.4999532670656825e+00</V>
   <V>X1.X1.P2: 2.7997495647382102e+01</V>
   <V>X1.X1.P3: 0.0000000000000000e+00</V>
   <V>X1.X1.Q1.N__3: 2.7867990980068758e+01</V>
   <V>X1.X1.Q1.N__6: 0.0000000000000000e+00</V>
   <V>X1.X1.Q1.N__7: 0.0000000000000000e+00</V>
   <V>X1.X1.Q1.P1: -2.4999522674113339e+00</V>
   <V>X1.X1.Q1.P2: 2.7981065896456666e+01</V>
   <V>X1.X1.Q1.P3: 0.0000000000000000e+00</V>
   <V>X1.X1.Q1.X1.N__12: 4.0383919511780407e-05</V>
   <V>X1.X1.Q1.X1.N__17: 2.7867990980068758e+01</V>
   <V>X1.X1.Q1.X1.N__2: -2.4999523662902017e+00</V>
   <V>X1.X1.Q1.X1.N__3: -2.4999523662902017e+00</V>
   <V>X1.X1.Q1.X1.N__5: 4.0382185424901047e-05</V>
   <V>X1.X1.Q1.X1.N__6: -2.4999523662902017e+00</V>
   <V>X1.X1.Q1.X1.N__8: -2.4999523662902017e+00</V>
   <V>X1.X1.Q1.X1.P1: -2.4999522674113339e+00</V>
   <V>X1.X1.Q1.X1.P2: 2.7981065896456666e+01</V>
   <V>X1.X1.Q1.X1.P3: 0.0000000000000000e+00</V>
   <V>X1.X1.Q1.X1.P4: 0.0000000000000000e+00</V>
   <V>X1.X1.Q1.X1.P5: 0.0000000000000000e+00</V>
   <V>X1.X1.Q1.X1.P6: 2.7867990980068758e+01</V>
   <V>X1.X1.Q1.X1.P7: 2.7867990980068758e+01</V>
   <V>X1.X1.Q1.X1.P8: 6.4823990061840945e+01</V>
   <V>X1.X1.Q1.X1.SRC1.neg: 0.0000000000000000e+00</V>
   <V>X1.X1.Q1.X1.SRC1.nsens: 4.0382185424901047e-05</V>
   <V>X1.X1.Q1.X1.SRC1.pos: -2.4999927484756266e+00</V>
   <V>X1.X1.Q1.X1.SRC1.psens: -2.4999523662902017e+00</V>
   <V>X1.X1.Q1.X1.SRL3.in: 4.0383921530976381e-05</V>
   <V>X1.X1.Q1.X1.SRL3.out: 0.0000000000000000e+00</V>
   <V>X1.X1.Q1.X1.X12.P1: -2.4999523662902017e+00</V>
   <V>X1.X1.Q1.X1.X12.P2: 4.0382185424901047e-05</V>
   <V>X1.X1.Q1.X1.X15.P1: -2.4999523662902017e+00</V>
   <V>X1.X1.Q1.X1.X15.P2: 2.7867990980068758e+01</V>
   <V>X1.X1.Q1.X1.vd1g: 4.0383921530976381e-05</V>
   <V>X1.X1.Q1.X1.vg1: -2.4999927484756266e+00</V>
   <V>X1.X1.Q1.dT: 6.4823990061840945e+01</V>
   <V>X1.X1.Q1.vdi: 2.7867990980068758e+01</V>
   <V>X1.X2.C1.N__1: 0.0000000000000000e+00</V>
   <V>X1.X2.C1.P1: 0.0000000000000000e+00</V>
   <V>X1.X2.C1.P2: 2.7999299547969944e+01</V>
   <V>X1.X2.C2._net1: 0.0000000000000000e+00</V>
   <V>X1.X2.C2._net2: 2.7999671583371210e+01</V>
   <V>X1.X2.C3._net1: 0.0000000000000000e+00</V>
   <V>X1.X2.C3._net2: 2.7999857601068204e+01</V>
   <V>X1.X2.C4.N__1: 0.0000000000000000e+00</V>
   <V>X1.X2.C4.P1: 0.0000000000000000e+00</V>
   <V>X1.X2.C4.P2: 2.7999485565671026e+01</V>
   <V>X1.X2.N__10: 2.7999113530268819e+01</V>
   <V>X1.X2.N__13: 2.7999901219893545e+01</V>
   <V>X1.X2.N__14: 2.7999485565671026e+01</V>
   <V>X1.X2.N__15: 2.7999813982268051e+01</V>
   <V>X1.X2.N__16: 2.7999715202180600e+01</V>
   <V>X1.X2.N__18: 2.7999671583371210e+01</V>
   <V>X1.X2.N__19: 2.7999529184478742e+01</V>
   <V>X1.X2.N__2: 2.7999857601068204e+01</V>
   <V>X1.X2.N__20: 2.7999627964564322e+01</V>
   <V>X1.X2.N__3: 2.7999441946863289e+01</V>
   <V>X1.X2.N__5: 2.7999343166777678e+01</V>
   <V>X1.X2.N__6: 2.7999069911461056e+01</V>
   <V>X1.X2.N__7: 2.7999299547969944e+01</V>
   <V>X1.X2.N__8: 2.7999255929162196e+01</V>
   <V>X1.X2.N__9: 2.7999157149076566e+01</V>
   <V>X1.X2.bias: 2.7997821066844953e+01</V>
   <V>X1.X2.vdd: 2.8000000000000000e+01</V>
   <V>X1.X3.C1.N__1: 0.0000000000000000e+00</V>
   <V>X1.X3.C1.P1: 0.0000000000000000e+00</V>
   <V>X1.X3.C1.P2: -2.4999999943710072e+00</V>
   <V>X1.X3.C4.N__1: 0.0000000000000000e+00</V>
   <V>X1.X3.C4.P1: 0.0000000000000000e+00</V>
   <V>X1.X3.C4.P2: -2.4999999958650929e+00</V>
   <V>X1.X3.C5._net1: 0.0000000000000000e+00</V>
   <V>X1.X3.C5._net2: -2.4999999973591005e+00</V>
   <V>X1.X3.C6._net1: 0.0000000000000000e+00</V>
   <V>X1.X3.C6._net2: -2.4999999988528234e+00</V>
   <V>X1.X3.N__10: -2.4999999928769161e+00</V>
   <V>X1.X3.N__13: -2.4999999992047397e+00</V>
   <V>X1.X3.N__14: -2.4999999958650929e+00</V>
   <V>X1.X3.N__15: -2.4999999985031565e+00</V>
   <V>X1.X3.N__16: -2.4999999977095926e+00</V>
   <V>X1.X3.N__19: -2.4999999962154362e+00</V>
   <V>X1.X3.N__2: -2.4999999973591005e+00</V>
   <V>X1.X3.N__20: -2.4999999970088322e+00</V>
   <V>X1.X3.N__23: -2.4999999988528234e+00</V>
   <V>X1.X3.N__3: -2.4999999955147492e+00</V>
   <V>X1.X3.N__5: -2.4999999947213514e+00</V>
   <V>X1.X3.N__6: -2.4999999925265701e+00</V>
   <V>X1.X3.N__7: -2.4999999943710072e+00</V>
   <V>X1.X3.N__8: -2.4999999940206621e+00</V>
   <V>X1.X3.N__9: -2.4999999932272616e+00</V>
   <V>X1.X3.bias: -2.4999999824958592e+00</V>
   <V>X1.X3.vdd: -2.5000000000000000e+00</V>
   <V>X1.X4.N__0: 0.0000000000000000e+00</V>
   <V>X1.X4.N__10: 0.0000000000000000e+00</V>
   <V>X1.X4.N__11: 0.0000000000000000e+00</V>
   <V>X1.X4.N__12: 0.0000000000000000e+00</V>
   <V>X1.X4.N__13: 0.0000000000000000e+00</V>
   <V>X1.X4.N__14: 0.0000000000000000e+00</V>
   <V>X1.X4.N__15: 0.0000000000000000e+00</V>
   <V>X1.X4.N__6: 0.0000000000000000e+00</V>
   <V>X1.X4.N__7: 0.0000000000000000e+00</V>
   <V>X1.X4.N__8: 0.0000000000000000e+00</V>
   <V>X1.X4.N__9: 0.0000000000000000e+00</V>
   <V>X1.X4.in: 0.0000000000000000e+00</V>
   <V>X1.X4.out: 0.0000000000000000e+00</V>
   <V>X1.X5.N__10: 0.0000000000000000e+00</V>
   <V>X1.X5.N__11: 0.0000000000000000e+00</V>
   <V>X1.X5.N__12: 0.0000000000000000e+00</V>
   <V>X1.X5.N__13: 0.0000000000000000e+00</V>
   <V>X1.X5.N__14: 0.0000000000000000e+00</V>
   <V>X1.X5.N__16: 0.0000000000000000e+00</V>
   <V>X1.X5.N__17: 0.0000000000000000e+00</V>
   <V>X1.X5.N__19: 0.0000000000000000e+00</V>
   <V>X1.X5.N__22: 0.0000000000000000e+00</V>
   <V>X1.X5.N__4: 0.0000000000000000e+00</V>
   <V>X1.X5.N__5: 0.0000000000000000e+00</V>
   <V>X1.X5.N__6: 0.0000000000000000e+00</V>
   <V>X1.X5.N__7: 0.0000000000000000e+00</V>
   <V>X1.X5.N__8: 0.0000000000000000e+00</V>
   <V>X1.X5.N__9: 0.0000000000000000e+00</V>
   <V>X1.X5.in: 0.0000000000000000e+00</V>
   <V>X1.X5.out: 0.0000000000000000e+00</V>
   <V>X1.vdrain: 2.8000000000000000e+01</V>
   <V>X1.vgate: -2.5000000000000000e+00</V>
   <V>X1.vin: 0.0000000000000000e+00</V>
   <V>X1.vout: 0.0000000000000000e+00</V>
   <GV>0: 0.0000000000000000e+00</GV>
  </DC_Voltages>
  <DC_PinCurrents>
   <I>SRC1: 2.3411070222611358e-06, -2.3411070222611358e-06</I>
   <I>SRC2: -2.9079211293107654e-01, 2.9079211293107654e-01</I>
   <I>Term1: 0.0000000000000000e+00, 0.0000000000000000e+00</I>
   <I>Term2: 0.0000000000000000e+00, 0.0000000000000000e+00</I>
   <I>X1: 0.0000000000000000e+00, 0.0000000000000000e+00, -2.3411070222611358e-06, 2.9079211293107654e-01</I>
   <I>X1.Gap1: 0.0000000000000000e+00, 0.0000000000000000e+00</I>
   <I>X1.Gap2: 0.0000000000000000e+00, 0.0000000000000000e+00</I>
   <I>X1.Gap3: 0.0000000000000000e+00, 0.0000000000000000e+00</I>
   <I>X1.Gap4: 0.0000000000000000e+00, 0.0000000000000000e+00</I>
   <I>X1.Gap5: 0.0000000000000000e+00, 0.0000000000000000e+00</I>
   <I>X1.Kap1: 0.0000000000000000e+00, 0.0000000000000000e+00</I>
   <I>X1.Kap1.C10: 0.0000000000000000e+00, 0.0000000000000000e+00</I>
   <I>X1.Kap1.C7: 0.0000000000000000e+00, 0.0000000000000000e+00</I>
   <I>X1.Kap1.C9: 0.0000000000000000e+00, 0.0000000000000000e+00</I>
   <I>X1.Kap1.L1: 0.0000000000000000e+00, 0.0000000000000000e+00</I>
   <I>X1.Kap2: 0.0000000000000000e+00, 0.0000000000000000e+00</I>
   <I>X1.Kap2.C10: 0.0000000000000000e+00, 0.0000000000000000e+00</I>
   <I>X1.Kap2.C7: 0.0000000000000000e+00, 0.0000000000000000e+00</I>
   <I>X1.Kap2.C9: 0.0000000000000000e+00, 0.0000000000000000e+00</I>
   <I>X1.Kap2.L1: 0.0000000000000000e+00, 0.0000000000000000e+00</I>
   <I>X1.Kap3: 0.0000000000000000e+00, 0.0000000000000000e+00</I>
   <I>X1.Kap3.C10: 0.0000000000000000e+00, 0.0000000000000000e+00</I>
   <I>X1.Kap3.C7: 0.0000000000000000e+00, 0.0000000000000000e+00</I>
   <I>X1.Kap3.C9: 0.0000000000000000e+00, 0.0000000000000000e+00</I>
   <I>X1.Kap3.L1: 0.0000000000000000e+00, 0.0000000000000000e+00</I>
   <I>X1.R1: -2.3356419116993267e-06, 2.3356419116993267e-06</I>
   <I>X1.R2: -2.3356397289564512e-06, 2.3356397289564512e-06</I>
   <I>X1.TL1: -2.3356419117108862e-06, 2.3356410022220421e-06</I>
   <I>X1.TL2: -2.9079205177766115e-01, 2.9079205178694090e-01</I>
   <I>X1.TL3: -7.3335968403949000e-11, 0.0000000000000000e+00</I>
   <I>X1.Taper1: 0.0000000000000000e+00, 0.0000000000000000e+00</I>
   <I>X1.Taper3: 0.0000000000000000e+00, 0.0000000000000000e+00</I>
   <I>X1.Taper4: 2.1827784024283228e-12, 0.0000000000000000e+00</I>
   <I>X1.Tee1: 7.2759576141834259e-11, -2.9079205180460121e-01, 2.9079205171728972e-01</I>
   <I>X1.Tee2: 2.3356424208031967e-06, -1.8189894035458565e-12, -2.3356406018137932e-06</I>
   <I>X1.X1: -2.3356410022220421e-06, 2.9079205177766115e-01, -2.9076423502302989e-01</I>
   <I>X1.X2: -2.9079205171360495e-01, 2.9079211293107654e-01</I>
   <I>X1.X2.C1: 0.0000000000000000e+00, 0.0000000000000000e+00</I>
   <I>X1.X2.C1.C10: 0.0000000000000000e+00, 0.0000000000000000e+00</I>
   <I>X1.X2.C1.C7: 0.0000000000000000e+00, 0.0000000000000000e+00</I>
   <I>X1.X2.C1.L1: 0.0000000000000000e+00, 0.0000000000000000e+00</I>
   <I>X1.X2.C2: -5.5999338903481780e-09, 5.5999338903481780e-09</I>
   <I>X1.X2.C2.Z1P01: -5.5999338903481780e-09, 5.5999338903481780e-09</I>
   <I>X1.X2.C3: -5.5999653867469460e-08, 5.5999653867469460e-08</I>
   <I>X1.X2.C3.Z1P01: -5.5999653867469460e-08, 5.5999653867469460e-08</I>
   <I>X1.X2.C4: 0.0000000000000000e+00, 0.0000000000000000e+00</I>
   <I>X1.X2.C4.C10: 0.0000000000000000e+00, 0.0000000000000000e+00</I>
   <I>X1.X2.C4.C7: 0.0000000000000000e+00, 0.0000000000000000e+00</I>
   <I>X1.X2.C4.L1: 0.0000000000000000e+00, 0.0000000000000000e+00</I>
   <I>X1.X2.Gap1: 0.0000000000000000e+00, 0.0000000000000000e+00</I>
   <I>X1.X2.Gap2: 0.0000000000000000e+00, 0.0000000000000000e+00</I>
   <I>X1.X2.Stub1: 2.4919188235666494e-12</I>
   <I>X1.X2.TL3: 2.9079205171165035e-01, -2.9079205171360495e-01</I>
   <I>X1.X2.TL5: -2.9079205169959033e-01, 2.9079205162888139e-01</I>
   <I>X1.X2.TL6: -2.9079205162888139e-01, 2.9079205155817195e-01</I>
   <I>X1.X2.TL7: -2.9079205154362003e-01, 2.9079205147291010e-01</I>
   <I>X1.X2.TL8: -2.9079205705829209e-01, 2.9079205698758165e-01</I>
   <I>X1.X2.TL9: -2.9079211300178748e-01, 2.9079211293107654e-01</I>
   <I>X1.X2.Tee1: 2.9079205173184164e-01, -2.9079205173184164e-01, 0.0000000000000000e+00</I>
   <I>X1.X2.Tee2: 2.9079205161542632e-01, -2.9079205162997823e-01, 0.0000000000000000e+00</I>
   <I>X1.X2.Tee3: 2.9079205152811483e-01, -2.9079205155721866e-01, 2.9103830456733704e-11</I>
   <I>X1.X2.Tee4: 2.9079205707239453e-01, -2.9079205148445908e-01, -5.5879354476928711e-09</I>
   <I>X1.X2.Tee5: 2.9079211299540475e-01, -2.9079205699963495e-01, -5.5995769798755646e-08</I>
   <I>X1.X3: 2.3356397289324836e-06, -2.3411070222611358e-06</I>
   <I>X1.X3.C1: 0.0000000000000000e+00, 0.0000000000000000e+00</I>
   <I>X1.X3.C1.C10: 0.0000000000000000e+00, 0.0000000000000000e+00</I>
   <I>X1.X3.C1.C7: 0.0000000000000000e+00, 0.0000000000000000e+00</I>
   <I>X1.X3.C1.L1: 0.0000000000000000e+00, 0.0000000000000000e+00</I>
   <I>X1.X3.C4: 0.0000000000000000e+00, 0.0000000000000000e+00</I>
   <I>X1.X3.C4.C10: 0.0000000000000000e+00, 0.0000000000000000e+00</I>
   <I>X1.X3.C4.C7: 0.0000000000000000e+00, 0.0000000000000000e+00</I>
   <I>X1.X3.C4.L1: 0.0000000000000000e+00, 0.0000000000000000e+00</I>
   <I>X1.X3.C5: 4.9999996140654656e-10, -4.9999996140654656e-10</I>
   <I>X1.X3.C5.Z1P01: 4.9999996140654656e-10, -4.9999996140654656e-10</I>
   <I>X1.X3.C6: 4.9999945213682499e-09, -4.9999945213682499e-09</I>
   <I>X1.X3.C6.Z1P01: 4.9999945213682499e-09, -4.9999945213682499e-09</I>
   <I>X1.X3.Gap1: 0.0000000000000000e+00, 0.0000000000000000e+00</I>
   <I>X1.X3.Gap2: 0.0000000000000000e+00, 0.0000000000000000e+00</I>
   <I>X1.X3.Stub1: -2.2249979573216387e-13</I>
   <I>X1.X3.TL3: -2.3356395470313840e-06, 2.3356397289324836e-06</I>
   <I>X1.X3.TL5: 2.3356397695311797e-06, -2.3356332211722258e-06</I>
   <I>X1.X3.TL6: 2.3356314021828222e-06, -2.3356248538366339e-06</I>
   <I>X1.X3.TL7: 2.3356266728260374e-06, -2.3356201244776837e-06</I>
   <I>X1.X3.TL8: 2.3361201244390901e-06, -2.3361135760892426e-06</I>
   <I>X1.X3.TL9: 2.3411135706106110e-06, -2.3411070222611358e-06</I>
   <I>X1.X3.Tee1: -2.3356406018137932e-06, 2.3356406018137932e-06, 1.8189894035458565e-12</I>
   <I>X1.X3.Tee2: -2.3356333258561790e-06, 2.3356333258561790e-06, 0.0000000000000000e+00</I>
   <I>X1.X3.Tee3: -2.3356260498985648e-06, 2.3356242309091613e-06, 1.8189894035458565e-12</I>
   <I>X1.X3.Tee4: -2.3361208150163293e-06, 2.3356205929303542e-06, 5.0022208597511053e-10</I>
   <I>X1.X3.Tee5: -2.3411121219396591e-06, 2.3361117200693116e-06, 5.0004018703475595e-09</I>
   <I>X1.X4: 0.0000000000000000e+00, 0.0000000000000000e+00</I>
   <I>X1.X4.CLin1: 0.0000000000000000e+00, 0.0000000000000000e+00, 0.0000000000000000e+00, 0.0000000000000000e+00</I>
   <I>X1.X4.Curve1: 0.0000000000000000e+00, 0.0000000000000000e+00</I>
   <I>X1.X4.Curve2: 0.0000000000000000e+00, 0.0000000000000000e+00</I>
   <I>X1.X4.Curve3: 0.0000000000000000e+00, 0.0000000000000000e+00</I>
   <I>X1.X4.Curve4: 0.0000000000000000e+00, 0.0000000000000000e+00</I>
   <I>X1.X4.TL12: 0.0000000000000000e+00</I>
   <I>X1.X4.TL16: 0.0000000000000000e+00, 0.0000000000000000e+00</I>
   <I>X1.X4.TL22: 0.0000000000000000e+00, 0.0000000000000000e+00</I>
   <I>X1.X4.Taper1: 0.0000000000000000e+00, 0.0000000000000000e+00</I>
   <I>X1.X4.Taper2: 0.0000000000000000e+00, 0.0000000000000000e+00</I>
   <I>X1.X4.Tee1: 0.0000000000000000e+00, 0.0000000000000000e+00, 0.0000000000000000e+00</I>
   <I>X1.X5: 0.0000000000000000e+00, 0.0000000000000000e+00</I>
   <I>X1.X5.CLin1: 0.0000000000000000e+00, 0.0000000000000000e+00, 0.0000000000000000e+00, 0.0000000000000000e+00</I>
   <I>X1.X5.Curve1: 0.0000000000000000e+00, 0.0000000000000000e+00</I>
   <I>X1.X5.Curve2: 0.0000000000000000e+00, 0.0000000000000000e+00</I>
   <I>X1.X5.Curve3: 0.0000000000000000e+00, 0.0000000000000000e+00</I>
   <I>X1.X5.Curve4: 0.0000000000000000e+00, 0.0000000000000000e+00</I>
   <I>X1.X5.Curve5: 0.0000000000000000e+00, 0.0000000000000000e+00</I>
   <I>X1.X5.TL16: 0.0000000000000000e+00, 0.0000000000000000e+00</I>
   <I>X1.X5.TL21: 0.0000000000000000e+00, 0.0000000000000000e+00</I>
   <I>X1.X5.TL22: 0.0000000000000000e+00, 0.0000000000000000e+00</I>
   <I>X1.X5.TL23: 0.0000000000000000e+00, 0.0000000000000000e+00</I>
   <I>X1.X5.TL9: 0.0000000000000000e+00, 0.0000000000000000e+00</I>
   <I>X1.X5.Taper1: 0.0000000000000000e+00, 0.0000000000000000e+00</I>
   <I>X1.X5.Taper2: 0.0000000000000000e+00, 0.0000000000000000e+00</I>
   <I>X1.X5.Tee1: 0.0000000000000000e+00, 0.0000000000000000e+00, 0.0000000000000000e+00</I>
   <I>X1.X5.V1: 0.0000000000000000e+00, 0.0000000000000000e+00</I>
  </DC_PinCurrents>
  <DC_OPInstances/>
 </Controller>
</DCOPData>
